LICENSE.txt
README.rst
pyproject.toml
openet/__init__.py
openet/ssebop/__init__.py
openet/ssebop/collection.py
openet/ssebop/image.py
openet/ssebop/interpolate.py
openet/ssebop/ipytest.py
openet/ssebop/landsat.py
openet/ssebop/model.py
openet/ssebop/utils.py
openet/ssebop/tests/conftest.py
openet/ssebop/tests/test_a_utils.py
openet/ssebop/tests/test_b_landsat.py
openet/ssebop/tests/test_b_model.py
openet/ssebop/tests/test_c_image.py
openet/ssebop/tests/test_d_collection.py
openet/ssebop/tests/test_d_interpolate.py
openet_ssebop.egg-info/PKG-INFO
openet_ssebop.egg-info/SOURCES.txt
openet_ssebop.egg-info/dependency_links.txt
openet_ssebop.egg-info/requires.txt
openet_ssebop.egg-info/top_level.txt