Metadata-Version: 2.4
Name: openet-ssebop
Version: 0.7.0
Summary: Earth Engine implementation of the SSEBop model
Author-email: Gabe Parrish <gparrish@contractor.usgs.gov>, Mac Friedrichs <mfriedrichs@contractor.usgs.gov>, Gabriel Senay <senay@usgs.gov>
Maintainer-email: Charles Morton <charles.morton@dri.edu>
License:                                  Apache License
Project-URL: Homepage, https://github.com/Open-ET/openet-ssebop
Keywords: SSEBop,OpenET,Earth Engine,Evapotranspiration,Landsat
Classifier: Programming Language :: Python :: 3
Classifier: License :: OSI Approved :: Apache Software License
Classifier: Operating System :: OS Independent
Requires-Python: >=3.9
License-File: LICENSE.txt
Requires-Dist: earthengine-api>=1.5.2
Requires-Dist: openet-core>=0.7.0
Requires-Dist: openet-refet-gee>=0.6.2
Requires-Dist: python-dateutil
Provides-Extra: test
Requires-Dist: pytest; extra == "test"
Dynamic: license-file
